{
  "version": "0.3.3",
  "flags": {},
  "shapes": [
    {
      "label": "hermit crab",
      "points": [
        [
          836.99904,
          281.99987999999996
        ],
        [
          836.99904,
          290.99952
        ],
        [
          831.00096,
          297.0
        ],
        [
          825.0009600000001,
          297.0
        ],
        [
          822.0,
          300.00024
        ],
        [
          818.99904,
          300.00024
        ],
        [
          816.0,
          303.00048000000004
        ],
        [
          813.00096,
          303.00048000000004
        ],
        [
          801.00096,
          315.00036
        ],
        [
          798.0,
          315.00036
        ],
        [
          776.99904,
          335.99988
        ],
        [
          774.0,
          335.99988
        ],
        [
          758.99904,
          351.0
        ],
        [
          756.0,
          351.0
        ],
        [
          756.0,
          354.00024
        ],
        [
          734.9990399999999,
          374.99976
        ],
        [
          734.9990399999999,
          378.0
        ],
        [
          723.00096,
          389.99988
        ],
        [
          714.0,
          389.99988
        ],
        [
          714.0,
          470.99988
        ],
        [
          723.00096,
          470.99988
        ],
        [
          732.0,
          479.99952
        ],
        [
          732.0,
          486.0
        ],
        [
          734.9990399999999,
          489.00024
        ],
        [
          734.9990399999999,
          492.00048000000004
        ],
        [
          746.99904,
          504.00036
        ],
        [
          746.99904,
          506.99951999999996
        ],
        [
          750.0,
          509.99976
        ],
        [
          753.00096,
          509.99976
        ],
        [
          768.0,
          524.99988
        ],
        [
          768.0,
          528.00012
        ],
        [
          771.00096,
          531.00036
        ],
        [
          771.00096,
          551.99988
        ],
        [
          768.0,
          555.00012
        ],
        [
          768.0,
          563.9997599999999
        ],
        [
          765.0009600000001,
          567.0
        ],
        [
          765.0009600000001,
          573.00048
        ],
        [
          762.0,
          575.9996399999999
        ],
        [
          762.0,
          578.99988
        ],
        [
          758.99904,
          582.0001199999999
        ],
        [
          758.99904,
          585.00036
        ],
        [
          756.0,
          587.9995200000001
        ],
        [
          756.0,
          597.00024
        ],
        [
          753.00096,
          600.00048
        ],
        [
          753.00096,
          602.99964
        ],
        [
          750.0,
          605.9998800000001
        ],
        [
          750.0,
          612.00036
        ],
        [
          746.99904,
          614.99952
        ],
        [
          746.99904,
          624.00024
        ],
        [
          744.0,
          627.0004799999999
        ],
        [
          744.0,
          641.99952
        ],
        [
          746.99904,
          644.99976
        ],
        [
          746.99904,
          648.0
        ],
        [
          758.99904,
          659.99988
        ],
        [
          762.0,
          659.99988
        ],
        [
          768.0,
          666.00036
        ],
        [
          771.00096,
          666.00036
        ],
        [
          774.0,
          668.99952
        ],
        [
          776.99904,
          668.99952
        ],
        [
          780.0,
          671.99976
        ],
        [
          783.00096,
          671.99976
        ],
        [
          788.99904,
          678.00024
        ],
        [
          792.0,
          678.00024
        ],
        [
          794.9990399999999,
          681.00048
        ],
        [
          804.0,
          681.00048
        ],
        [
          806.99904,
          683.99964
        ],
        [
          813.00096,
          683.99964
        ],
        [
          818.99904,
          690.00012
        ],
        [
          818.99904,
          698.9997599999999
        ],
        [
          960.0,
          698.9997599999999
        ],
        [
          960.0,
          690.00012
        ],
        [
          966.0000000000001,
          683.99964
        ],
        [
          974.99904,
          683.99964
        ],
        [
          978.0,
          681.00048
        ],
        [
          987.0009600000001,
          681.00048
        ],
        [
          998.99904,
          668.99952
        ],
        [
          1002.0,
          668.99952
        ],
        [
          1002.0,
          666.00036
        ],
        [
          1005.00096,
          663.00012
        ],
        [
          1005.00096,
          659.99988
        ],
        [
          1011.00096,
          654.0004799999999
        ],
        [
          1011.00096,
          651.0002400000001
        ],
        [
          1013.9999999999999,
          648.0
        ],
        [
          1013.9999999999999,
          644.99976
        ],
        [
          1017.0009600000001,
          641.99952
        ],
        [
          1017.0009600000001,
          632.9998800000001
        ],
        [
          1020.0,
          629.99964
        ],
        [
          1020.0,
          627.0004799999999
        ],
        [
          1022.9990399999999,
          624.00024
        ],
        [
          1022.9990399999999,
          621.0
        ],
        [
          1026.0,
          617.99976
        ],
        [
          1026.0,
          614.99952
        ],
        [
          1028.99904,
          612.00036
        ],
        [
          1028.99904,
          605.9998800000001
        ],
        [
          1032.0,
          602.99964
        ],
        [
          1032.0,
          600.00048
        ],
        [
          1034.9990400000002,
          597.00024
        ],
        [
          1047.00096,
          597.00024
        ],
        [
          1047.00096,
          452.99951999999996
        ],
        [
          1034.9990400000002,
          452.99951999999996
        ],
        [
          1028.99904,
          447.00012
        ],
        [
          1028.99904,
          443.99988
        ],
        [
          1022.9990399999999,
          438.00048000000004
        ],
        [
          1022.9990399999999,
          428.99976000000004
        ],
        [
          1020.0,
          425.99952
        ],
        [
          1020.0,
          423.00036
        ],
        [
          1017.0009600000001,
          420.00012
        ],
        [
          1017.0009600000001,
          416.99987999999996
        ],
        [
          1013.9999999999999,
          413.99964
        ],
        [
          1013.9999999999999,
          411.00048
        ],
        [
          1011.00096,
          411.00048
        ],
        [
          1002.0,
          401.99976
        ],
        [
          1002.0,
          398.99952
        ],
        [
          981.00096,
          378.0
        ],
        [
          981.00096,
          374.99976
        ],
        [
          978.0,
          371.99951999999996
        ],
        [
          974.99904,
          371.99951999999996
        ],
        [
          968.99904,
          366.00012
        ],
        [
          968.99904,
          362.99988
        ],
        [
          966.0000000000001,
          359.99964
        ],
        [
          962.9990399999999,
          359.99964
        ],
        [
          954.0,
          351.0
        ],
        [
          951.00096,
          351.0
        ],
        [
          948.0,
          347.99976000000004
        ],
        [
          945.0009600000001,
          347.99976000000004
        ],
        [
          942.0,
          344.99952
        ],
        [
          938.99904,
          344.99952
        ],
        [
          933.00096,
          339.00012
        ],
        [
          930.0,
          339.00012
        ],
        [
          926.99904,
          335.99988
        ],
        [
          918.0,
          335.99988
        ],
        [
          914.9990399999999,
          332.99964
        ],
        [
          912.0,
          332.99964
        ],
        [
          908.99904,
          330.00048
        ],
        [
          906.0,
          330.00048
        ],
        [
          896.99904,
          320.99976
        ],
        [
          894.0,
          320.99976
        ],
        [
          885.0009600000001,
          312.00012
        ],
        [
          885.0009600000001,
          308.99988
        ],
        [
          873.00096,
          297.0
        ],
        [
          873.00096,
          293.99976000000004
        ],
        [
          870.0,
          290.99952
        ],
        [
          870.0,
          281.99987999999996
        ]
      ],
      "group_id": null,
      "shape_type": "polygon",
      "flags": {}
    },
    {
      "label": "close-up",
      "points": [
        [
          0.0,
          0.0
        ],
        [
          0.0,
          1080.0
        ],
        [
          1917.00096,
          1080.0
        ],
        [
          1917.00096,
          285.00012
        ],
        [
          1914.0,
          285.00012
        ],
        [
          1908.0,
          278.99964
        ],
        [
          1908.0,
          276.00048
        ],
        [
          1905.0009599999998,
          273.00024
        ],
        [
          1905.0009599999998,
          270.0
        ],
        [
          1896.0,
          261.00036
        ],
        [
          1896.0,
          258.00012
        ],
        [
          1892.99904,
          254.99988
        ],
        [
          1892.99904,
          251.99964
        ],
        [
          1890.0,
          249.00048
        ],
        [
          1890.0,
          246.00024000000002
        ],
        [
          1884.0,
          239.99976
        ],
        [
          1884.0,
          236.99952
        ],
        [
          1881.00096,
          234.00036
        ],
        [
          1881.00096,
          231.00011999999998
        ],
        [
          1872.0,
          222.00047999999998
        ],
        [
          1872.0,
          219.00024000000002
        ],
        [
          1866.0,
          212.99976
        ],
        [
          1866.0,
          209.99952000000002
        ],
        [
          1860.0,
          204.00012
        ],
        [
          1860.0,
          200.99988
        ],
        [
          1857.00096,
          197.99964
        ],
        [
          1857.00096,
          195.00047999999998
        ],
        [
          1848.0,
          185.99975999999998
        ],
        [
          1848.0,
          182.99952000000002
        ],
        [
          1845.0009599999998,
          180.00036
        ],
        [
          1845.0009599999998,
          177.00012
        ],
        [
          1842.0,
          173.99988000000002
        ],
        [
          1842.0,
          170.99964
        ],
        [
          1832.99904,
          162.0
        ],
        [
          1832.99904,
          158.99975999999998
        ],
        [
          1830.0,
          155.99952
        ],
        [
          1830.0,
          153.00036
        ],
        [
          1821.00096,
          143.99964
        ],
        [
          1821.00096,
          141.00048
        ],
        [
          1812.0,
          131.99976
        ],
        [
          1812.0,
          128.99952
        ],
        [
          1808.99904,
          126.00036
        ],
        [
          1808.99904,
          123.00012000000001
        ],
        [
          1800.0,
          114.00048
        ],
        [
          1800.0,
          111.00023999999999
        ],
        [
          1797.00096,
          108.0
        ],
        [
          1797.00096,
          104.99997599999999
        ],
        [
          1788.0,
          96.00001200000001
        ],
        [
          1788.0,
          92.999988
        ],
        [
          1785.0009599999998,
          89.999964
        ],
        [
          1785.0009599999998,
          87.000048
        ],
        [
          1776.0,
          77.999976
        ],
        [
          1776.0,
          74.99995200000001
        ],
        [
          1770.0,
          69.000012
        ],
        [
          1770.0,
          65.999988
        ],
        [
          1764.0,
          60.000048
        ],
        [
          1764.0,
          57.000023999999996
        ],
        [
          1761.00096,
          54.0
        ],
        [
          1761.00096,
          50.999976
        ],
        [
          1752.0,
          42.000012
        ],
        [
          1752.0,
          38.999988
        ],
        [
          1748.99904,
          35.999964000000006
        ],
        [
          1748.99904,
          33.000048
        ],
        [
          1740.0,
          23.999976
        ],
        [
          1740.0,
          20.999952
        ],
        [
          1737.00096,
          18.000035999999998
        ],
        [
          1737.00096,
          15.000012
        ],
        [
          1728.0,
          6.0000048
        ],
        [
          1728.0,
          0.0
        ]
      ],
      "group_id": null,
      "shape_type": "polygon",
      "flags": {}
    },
    {
      "label": "crumb",
      "points": [
        [
          1245.0009599999998,
          293.99976000000004
        ],
        [
          1245.0009599999998,
          303.00048000000004
        ],
        [
          1242.0,
          305.99964
        ],
        [
          1230.0,
          305.99964
        ],
        [
          1230.0,
          339.00012
        ],
        [
          1242.0,
          339.00012
        ],
        [
          1245.0009599999998,
          342.00036
        ],
        [
          1245.0009599999998,
          351.0
        ],
        [
          1290.0,
          351.0
        ],
        [
          1290.0,
          339.00012
        ],
        [
          1292.99904,
          335.99988
        ],
        [
          1296.0,
          335.99988
        ],
        [
          1298.99904,
          332.99964
        ],
        [
          1302.0,
          332.99964
        ],
        [
          1314.0,
          320.99976
        ],
        [
          1322.99904,
          320.99976
        ],
        [
          1322.99904,
          312.00012
        ],
        [
          1308.0,
          312.00012
        ],
        [
          1305.0009599999998,
          308.99988
        ],
        [
          1302.0,
          308.99988
        ],
        [
          1298.99904,
          305.99964
        ],
        [
          1298.99904,
          293.99976000000004
        ]
      ],
      "group_id": null,
      "shape_type": "polygon",
      "flags": {}
    },
    {
      "label": "pollen",
      "points": [
        [
          921.00096,
          570.00024
        ],
        [
          921.00096,
          578.99988
        ],
        [
          918.0,
          582.0001199999999
        ],
        [
          906.0,
          582.0001199999999
        ],
        [
          906.0,
          614.99952
        ],
        [
          918.0,
          614.99952
        ],
        [
          921.00096,
          617.99976
        ],
        [
          921.00096,
          627.0004799999999
        ],
        [
          948.0,
          627.0004799999999
        ],
        [
          948.0,
          617.99976
        ],
        [
          954.0,
          612.00036
        ],
        [
          962.9990399999999,
          612.00036
        ],
        [
          962.9990399999999,
          570.00024
        ]
      ],
      "group_id": null,
      "shape_type": "polygon",
      "flags": {}
    },
    {
      "label": "sherbert",
      "points": [
        [
          836.99904,
          281.99987999999996
        ],
        [
          836.99904,
          290.99952
        ],
        [
          831.00096,
          297.0
        ],
        [
          828.0,
          297.0
        ],
        [
          825.0009600000001,
          300.00024
        ],
        [
          818.99904,
          300.00024
        ],
        [
          816.0,
          303.00048000000004
        ],
        [
          813.00096,
          303.00048000000004
        ],
        [
          801.00096,
          315.00036
        ],
        [
          798.0,
          315.00036
        ],
        [
          776.99904,
          335.99988
        ],
        [
          774.0,
          335.99988
        ],
        [
          758.99904,
          351.0
        ],
        [
          756.0,
          351.0
        ],
        [
          756.0,
          354.00024
        ],
        [
          734.9990399999999,
          374.99976
        ],
        [
          734.9990399999999,
          378.0
        ],
        [
          723.00096,
          389.99988
        ],
        [
          714.0,
          389.99988
        ],
        [
          714.0,
          470.99988
        ],
        [
          723.00096,
          470.99988
        ],
        [
          732.0,
          479.99952
        ],
        [
          732.0,
          482.99976000000004
        ],
        [
          734.9990399999999,
          486.0
        ],
        [
          734.9990399999999,
          492.00048000000004
        ],
        [
          746.99904,
          504.00036
        ],
        [
          746.99904,
          506.99951999999996
        ],
        [
          750.0,
          509.99976
        ],
        [
          753.00096,
          509.99976
        ],
        [
          768.0,
          524.99988
        ],
        [
          768.0,
          528.00012
        ],
        [
          771.00096,
          531.00036
        ],
        [
          771.00096,
          555.00012
        ],
        [
          768.0,
          558.00036
        ],
        [
          768.0,
          567.0
        ],
        [
          765.0009600000001,
          570.00024
        ],
        [
          765.0009600000001,
          573.00048
        ],
        [
          762.0,
          575.9996399999999
        ],
        [
          762.0,
          578.99988
        ],
        [
          758.99904,
          582.0001199999999
        ],
        [
          758.99904,
          587.9995200000001
        ],
        [
          756.0,
          590.99976
        ],
        [
          756.0,
          597.00024
        ],
        [
          753.00096,
          600.00048
        ],
        [
          753.00096,
          602.99964
        ],
        [
          750.0,
          605.9998800000001
        ],
        [
          750.0,
          612.00036
        ],
        [
          746.99904,
          614.99952
        ],
        [
          746.99904,
          624.00024
        ],
        [
          744.0,
          627.0004799999999
        ],
        [
          744.0,
          641.99952
        ],
        [
          746.99904,
          644.99976
        ],
        [
          746.99904,
          648.0
        ],
        [
          750.0,
          651.0002400000001
        ],
        [
          750.0,
          654.0004799999999
        ],
        [
          753.00096,
          654.0004799999999
        ],
        [
          758.99904,
          659.99988
        ],
        [
          762.0,
          659.99988
        ],
        [
          768.0,
          666.00036
        ],
        [
          771.00096,
          666.00036
        ],
        [
          774.0,
          668.99952
        ],
        [
          776.99904,
          668.99952
        ],
        [
          783.00096,
          675.0
        ],
        [
          786.0,
          675.0
        ],
        [
          788.99904,
          678.00024
        ],
        [
          792.0,
          678.00024
        ],
        [
          794.9990399999999,
          681.00048
        ],
        [
          801.00096,
          681.00048
        ],
        [
          804.0,
          683.99964
        ],
        [
          813.00096,
          683.99964
        ],
        [
          818.99904,
          690.00012
        ],
        [
          818.99904,
          698.9997599999999
        ],
        [
          960.0,
          698.9997599999999
        ],
        [
          960.0,
          690.00012
        ],
        [
          962.9990399999999,
          686.99988
        ],
        [
          966.0000000000001,
          686.99988
        ],
        [
          968.99904,
          683.99964
        ],
        [
          974.99904,
          683.99964
        ],
        [
          978.0,
          681.00048
        ],
        [
          987.0009600000001,
          681.00048
        ],
        [
          990.0,
          678.00024
        ],
        [
          992.9990399999999,
          678.00024
        ],
        [
          992.9990399999999,
          675.0
        ],
        [
          998.99904,
          668.99952
        ],
        [
          1002.0,
          668.99952
        ],
        [
          1005.00096,
          666.00036
        ],
        [
          1005.00096,
          659.99988
        ],
        [
          1013.9999999999999,
          651.0002400000001
        ],
        [
          1013.9999999999999,
          644.99976
        ],
        [
          1017.0009600000001,
          641.99952
        ],
        [
          1017.0009600000001,
          636.00012
        ],
        [
          1020.0,
          632.9998800000001
        ],
        [
          1020.0,
          627.0004799999999
        ],
        [
          1026.0,
          621.0
        ],
        [
          1026.0,
          614.99952
        ],
        [
          1028.99904,
          612.00036
        ],
        [
          1028.99904,
          609.0001199999999
        ],
        [
          1032.0,
          605.9998800000001
        ],
        [
          1032.0,
          602.99964
        ],
        [
          1038.0,
          597.00024
        ],
        [
          1047.00096,
          597.00024
        ],
        [
          1047.00096,
          452.99951999999996
        ],
        [
          1034.9990400000002,
          452.99951999999996
        ],
        [
          1028.99904,
          447.00012
        ],
        [
          1028.99904,
          443.99988
        ],
        [
          1022.9990399999999,
          438.00048000000004
        ],
        [
          1022.9990399999999,
          432.0
        ],
        [
          1020.0,
          428.99976000000004
        ],
        [
          1020.0,
          423.00036
        ],
        [
          1017.0009600000001,
          420.00012
        ],
        [
          1017.0009600000001,
          416.99987999999996
        ],
        [
          1002.0,
          401.99976
        ],
        [
          1002.0,
          398.99952
        ],
        [
          981.00096,
          378.0
        ],
        [
          981.00096,
          374.99976
        ],
        [
          978.0,
          371.99951999999996
        ],
        [
          974.99904,
          371.99951999999996
        ],
        [
          968.99904,
          366.00012
        ],
        [
          968.99904,
          362.99988
        ],
        [
          966.0000000000001,
          359.99964
        ],
        [
          962.9990399999999,
          359.99964
        ],
        [
          954.0,
          351.0
        ],
        [
          951.00096,
          351.0
        ],
        [
          948.0,
          347.99976000000004
        ],
        [
          945.0009600000001,
          347.99976000000004
        ],
        [
          942.0,
          344.99952
        ],
        [
          938.99904,
          344.99952
        ],
        [
          933.00096,
          339.00012
        ],
        [
          926.99904,
          339.00012
        ],
        [
          924.0,
          335.99988
        ],
        [
          918.0,
          335.99988
        ],
        [
          914.9990399999999,
          332.99964
        ],
        [
          912.0,
          332.99964
        ],
        [
          908.99904,
          330.00048
        ],
        [
          906.0,
          330.00048
        ],
        [
          896.99904,
          320.99976
        ],
        [
          894.0,
          320.99976
        ],
        [
          882.0,
          308.99988
        ],
        [
          882.0,
          305.99964
        ],
        [
          870.0,
          293.99976000000004
        ],
        [
          870.0,
          281.99987999999996
        ]
      ],
      "group_id": null,
      "shape_type": "polygon",
      "flags": {}
    },
    {
      "label": "drop",
      "points": [
        [
          813.00096,
          293.99976000000004
        ],
        [
          813.00096,
          305.99964
        ],
        [
          810.0,
          308.99988
        ],
        [
          806.99904,
          308.99988
        ],
        [
          798.0,
          317.99951999999996
        ],
        [
          794.9990399999999,
          317.99951999999996
        ],
        [
          794.9990399999999,
          320.99976
        ],
        [
          792.0,
          324.0
        ],
        [
          788.99904,
          324.0
        ],
        [
          774.0,
          339.00012
        ],
        [
          771.00096,
          339.00012
        ],
        [
          734.9990399999999,
          374.99976
        ],
        [
          734.9990399999999,
          378.0
        ],
        [
          723.00096,
          389.99988
        ],
        [
          714.0,
          389.99988
        ],
        [
          714.0,
          470.99988
        ],
        [
          723.00096,
          470.99988
        ],
        [
          732.0,
          479.99952
        ],
        [
          732.0,
          482.99976000000004
        ],
        [
          734.9990399999999,
          486.0
        ],
        [
          734.9990399999999,
          489.00024
        ],
        [
          738.0,
          492.00048000000004
        ],
        [
          738.0,
          494.99964
        ],
        [
          746.99904,
          504.00036
        ],
        [
          746.99904,
          506.99951999999996
        ],
        [
          750.0,
          509.99976
        ],
        [
          753.00096,
          509.99976
        ],
        [
          771.00096,
          528.00012
        ],
        [
          771.00096,
          558.00036
        ],
        [
          768.0,
          560.9995200000001
        ],
        [
          768.0,
          567.0
        ],
        [
          765.0009600000001,
          570.00024
        ],
        [
          765.0009600000001,
          575.9996399999999
        ],
        [
          758.99904,
          582.0001199999999
        ],
        [
          758.99904,
          587.9995200000001
        ],
        [
          756.0,
          590.99976
        ],
        [
          756.0,
          597.00024
        ],
        [
          753.00096,
          600.00048
        ],
        [
          753.00096,
          605.9998800000001
        ],
        [
          750.0,
          609.0001199999999
        ],
        [
          750.0,
          612.00036
        ],
        [
          746.99904,
          614.99952
        ],
        [
          746.99904,
          627.0004799999999
        ],
        [
          744.0,
          629.99964
        ],
        [
          744.0,
          641.99952
        ],
        [
          746.99904,
          644.99976
        ],
        [
          746.99904,
          648.0
        ],
        [
          756.0,
          656.99964
        ],
        [
          758.99904,
          656.99964
        ],
        [
          768.0,
          666.00036
        ],
        [
          771.00096,
          666.00036
        ],
        [
          774.0,
          668.99952
        ],
        [
          776.99904,
          668.99952
        ],
        [
          780.0,
          671.99976
        ],
        [
          783.00096,
          671.99976
        ],
        [
          788.99904,
          678.00024
        ],
        [
          792.0,
          678.00024
        ],
        [
          794.9990399999999,
          681.00048
        ],
        [
          804.0,
          681.00048
        ],
        [
          806.99904,
          683.99964
        ],
        [
          813.00096,
          683.99964
        ],
        [
          818.99904,
          690.00012
        ],
        [
          818.99904,
          698.9997599999999
        ],
        [
          960.0,
          698.9997599999999
        ],
        [
          960.0,
          690.00012
        ],
        [
          966.0000000000001,
          683.99964
        ],
        [
          972.0,
          683.99964
        ],
        [
          974.99904,
          681.00048
        ],
        [
          987.0009600000001,
          681.00048
        ],
        [
          998.99904,
          668.99952
        ],
        [
          1002.0,
          668.99952
        ],
        [
          1002.0,
          666.00036
        ],
        [
          1005.00096,
          663.00012
        ],
        [
          1005.00096,
          659.99988
        ],
        [
          1011.00096,
          654.0004799999999
        ],
        [
          1011.00096,
          651.0002400000001
        ],
        [
          1013.9999999999999,
          648.0
        ],
        [
          1013.9999999999999,
          644.99976
        ],
        [
          1017.0009600000001,
          641.99952
        ],
        [
          1017.0009600000001,
          632.9998800000001
        ],
        [
          1020.0,
          629.99964
        ],
        [
          1020.0,
          627.0004799999999
        ],
        [
          1022.9990399999999,
          624.00024
        ],
        [
          1022.9990399999999,
          621.0
        ],
        [
          1026.0,
          617.99976
        ],
        [
          1026.0,
          614.99952
        ],
        [
          1028.99904,
          612.00036
        ],
        [
          1028.99904,
          609.0001199999999
        ],
        [
          1032.0,
          605.9998800000001
        ],
        [
          1032.0,
          602.99964
        ],
        [
          1038.0,
          597.00024
        ],
        [
          1047.00096,
          597.00024
        ],
        [
          1047.00096,
          452.99951999999996
        ],
        [
          1034.9990400000002,
          452.99951999999996
        ],
        [
          1028.99904,
          447.00012
        ],
        [
          1028.99904,
          443.99988
        ],
        [
          1022.9990399999999,
          438.00048000000004
        ],
        [
          1022.9990399999999,
          432.0
        ],
        [
          1020.0,
          428.99976000000004
        ],
        [
          1020.0,
          423.00036
        ],
        [
          1013.9999999999999,
          416.99987999999996
        ],
        [
          1013.9999999999999,
          413.99964
        ],
        [
          1002.0,
          401.99976
        ],
        [
          1002.0,
          398.99952
        ],
        [
          998.99904,
          398.99952
        ],
        [
          992.9990399999999,
          393.00012000000004
        ],
        [
          992.9990399999999,
          389.99988
        ],
        [
          968.99904,
          366.00012
        ],
        [
          968.99904,
          362.99988
        ],
        [
          966.0000000000001,
          359.99964
        ],
        [
          962.9990399999999,
          359.99964
        ],
        [
          954.0,
          351.0
        ],
        [
          951.00096,
          351.0
        ],
        [
          948.0,
          347.99976000000004
        ],
        [
          945.0009600000001,
          347.99976000000004
        ],
        [
          942.0,
          344.99952
        ],
        [
          938.99904,
          344.99952
        ],
        [
          936.0,
          342.00036
        ],
        [
          933.00096,
          342.00036
        ],
        [
          930.0,
          339.00012
        ],
        [
          926.99904,
          339.00012
        ],
        [
          924.0,
          335.99988
        ],
        [
          918.0,
          335.99988
        ],
        [
          914.9990399999999,
          332.99964
        ],
        [
          912.0,
          332.99964
        ],
        [
          908.99904,
          330.00048
        ],
        [
          906.0,
          330.00048
        ],
        [
          900.0,
          324.0
        ],
        [
          896.99904,
          324.0
        ],
        [
          878.99904,
          305.99964
        ],
        [
          878.99904,
          293.99976000000004
        ]
      ],
      "group_id": null,
      "shape_type": "polygon",
      "flags": {}
    },
    {
      "label": "drop",
      "points": [
        [
          1242.0,
          293.99976000000004
        ],
        [
          1242.0,
          303.00048000000004
        ],
        [
          1238.99904,
          305.99964
        ],
        [
          1230.0,
          305.99964
        ],
        [
          1230.0,
          339.00012
        ],
        [
          1242.0,
          339.00012
        ],
        [
          1245.0009599999998,
          342.00036
        ],
        [
          1245.0009599999998,
          351.0
        ],
        [
          1290.0,
          351.0
        ],
        [
          1290.0,
          339.00012
        ],
        [
          1292.99904,
          335.99988
        ],
        [
          1296.0,
          335.99988
        ],
        [
          1298.99904,
          332.99964
        ],
        [
          1302.0,
          332.99964
        ],
        [
          1314.0,
          320.99976
        ],
        [
          1322.99904,
          320.99976
        ],
        [
          1322.99904,
          312.00012
        ],
        [
          1308.0,
          312.00012
        ],
        [
          1298.99904,
          303.00048000000004
        ],
        [
          1298.99904,
          293.99976000000004
        ]
      ],
      "group_id": null,
      "shape_type": "polygon",
      "flags": {}
    }
  ],
  "imagePath": "WIN_20251115_13_41_04_Pro.jpg",
  "imageData": null,
  "imageHeight": 1080,
  "imageWidth": 1920
}